fshare_cli/__init__.py
fshare_cli/__main__.py
fshare_cli/fshare_api.py
fshare_cli/fshare_cli.py
fshare_cli/fshare_utils.py
fshare_cli/version.py
fshare_cli-2021.5.4.dist-info/AUTHORS
fshare_cli-2021.5.4.dist-info/LICENSE
fshare_cli-2021.5.4.dist-info/METADATA
fshare_cli-2021.5.4.dist-info/WHEEL
fshare_cli-2021.5.4.dist-info/entry_points.txt
fshare_cli-2021.5.4.dist-info/top_level.txt
fshare_cli-2021.5.4.dist-info/RECORD
